randomprefixgenerator/__init__.py
randomprefixgenerator/randomprefixgenerator.py
random_prefix_generator-0.4.dist-info/LICENSE
random_prefix_generator-0.4.dist-info/METADATA
random_prefix_generator-0.4.dist-info/WHEEL
random_prefix_generator-0.4.dist-info/top_level.txt
random_prefix_generator-0.4.dist-info/RECORD
