Metadata-Version: 2.1
Name: random-prefix-generator
Version: 0.4
Summary: A package for generating random IPv4 and IPv6 addresses and subnets
Home-page: https://github.com/colinmacgiolla/random_ip_generator
Author: Colin MacGiollaEain
Author-email: colin@flat-planet.net
Classifier: Development Status :: 4 - Beta
Classifier: Intended Audience :: Information Technology
Classifier: Topic :: System :: Networking
Classifier: Programming Language :: Python :: 3
Classifier: Programming Language :: Python :: 3.6
Classifier: Programming Language :: Python :: 3.7
Classifier: Programming Language :: Python :: 3.8
Classifier: Programming Language :: Python :: 3.9
Classifier: Programming Language :: Python :: 3 :: Only
Classifier: License :: OSI Approved :: BSD License
Classifier: Operating System :: OS Independent
Requires-Python: >=3.6
License-File: LICENSE
Requires-Dist: ipaddress
